[{"id": "6514440", "Name": "Dyson - Corrale Hair Straightener - Vinca Blue/Ros\u00e9", "Image": "https://pisces.bbystatic.com/image2/BestBuy_US/images/products/6514/6514440_rd.jpg", "Url": "https://www.bestbuy.com/site/dyson-corrale-hair-straightener-vinca-blue-rose/6514440.p?skuId=6514440", "Company": "BestBuy", "Mtype": "Beauty and Personal Care", "Subtype": "Haircare", "Price1": "$399.99", "Price2": "$499.99", "Off": 21}, {"id": null, "Name": "Wahl - Lithium Pro Complete Cordless Haircut Kit - Black/Silver", "Image": "https://pisces.bbystatic.com/image2/BestBuy_US/images/products/5191/5191100_rd.jpg", "Url": "https://www.bestbuy.com/site/wahl-lithium-pro-complete-cordless-haircut-kit-black-silver/5191100.p?skuId=5191100", "Company": "BestBuy", "Mtype": "Beauty and Personal Care", "Subtype": "Haircare", "Price1": "$59.99", "Price2": "$79.99", "Off": 26}, {"id": "5191100", "Name": "Wahl - Lithium Pro Complete Cordless Haircut Kit - Black/Silver", "Image": "https://pisces.bbystatic.com/image2/BestBuy_US/images/products/5191/5191100_rd.jpg", "Url": "https://www.bestbuy.com/site/wahl-lithium-pro-complete-cordless-haircut-kit-black-silver/5191100.p?skuId=5191100", "Company": "BestBuy", "Mtype": "Beauty and Personal Care", "Subtype": "Haircare", "Price1": "$59.99", "Price2": "$79.99", "Off": 26}, {"id": "6373034", "Name": "Conair - Cordless Titanium 1\u201d Curling Iron - Purple/Rose Gold", "Image": "https://pisces.bbystatic.com/image2/BestBuy_US/images/products/6373/6373034cv11d.jpg", "Url": "https://www.bestbuy.com/site/conair-cordless-titanium-1-curling-iron-purple-rose-gold/6373034.p?skuId=6373034", "Company": "BestBuy", "Mtype": "Beauty and Personal Care", "Subtype": "Haircare", "Price1": "$47.99", "Price2": "$59.99", "Off": 21}, {"id": "8611353", "Name": "Conair - Ion Instant Heat Hair Setter with 12 Jumbo Rollers", "Image": "https://pisces.bbystatic.com/image2/BestBuy_US/images/products/8611/8611353_rd.jpg", "Url": "https://www.bestbuy.com/site/conair-ion-instant-heat-hair-setter-with-12-jumbo-rollers/8611353.p?skuId=8611353", "Company": "BestBuy", "Mtype": "Beauty and Personal Care", "Subtype": "Haircare", "Price1": "$34.99", "Price2": "$47.99", "Off": 28}]